<?xml version="1.0" encoding="UTF-8"?>
<?xml-stylesheet type="text/css" href="abc.css"?>
<students>
    <student>
        <id>01</id>
        <name>Pratik Zende</name>
        <position>Designer</position>
        <department>Creative</department>
        <salary>50000</salary>
    </student>
    <student>
        <id>02</id>
        <name>Aniket Shinde</name>
        <position>Developer</position>
        <department>Engineering</department>
        <salary>75000</salary>
    </student>
</students>